docker_adapter/__init__.py
docker_adapter/client.py
docker_adapter/container.py
docker_adapter/exceptions.py
docker_adapter/image.py
evolvishub_docker_adapter-0.2.0.dist-info/METADATA
evolvishub_docker_adapter-0.2.0.dist-info/WHEEL
evolvishub_docker_adapter-0.2.0.dist-info/licenses/LICENSE
evolvishub_docker_adapter-0.2.0.dist-info/RECORD
