Metadata-Version: 2.4
Name: evolvishub-docker-adapter
Version: 0.2.0
Summary: A Docker adapter for EvolvisHub
Project-URL: Homepage, https://github.com/evolvis/docker-adapter
Project-URL: Documentation, https://docker-adapter.readthedocs.io/
Project-URL: Repository, https://github.com/evolvis/docker-adapter.git
Project-URL: Issues, https://github.com/evolvis/docker-adapter/issues
Author-email: EvolvisAI <info@evolvis.ai>
License-Expression: MIT
License-File: LICENSE
Classifier: Development Status :: 4 - Beta
Classifier: Intended Audience :: Developers
Classifier: License :: OSI Approved :: MIT License
Classifier: Programming Language :: Python :: 3
Classifier: Programming Language :: Python :: 3.10
Classifier: Programming Language :: Python :: 3.11
Classifier: Programming Language :: Python :: 3.12
Requires-Python: >=3.8
Requires-Dist: docker>=6.1.3
Requires-Dist: pydantic>=2.4.2
Requires-Dist: python-dotenv>=1.0.0
Requires-Dist: typing-extensions>=4.7.1
Provides-Extra: dev
Requires-Dist: black>=23.7.0; extra == 'dev'
Requires-Dist: isort>=5.12.0; extra == 'dev'
Requires-Dist: mypy>=1.5.1; extra == 'dev'
Requires-Dist: pytest-cov>=4.1.0; extra == 'dev'
Requires-Dist: pytest-mock>=3.11.1; extra == 'dev'
Requires-Dist: pytest>=7.4.0; extra == 'dev'
Requires-Dist: ruff>=0.0.284; extra == 'dev'
Requires-Dist: types-docker>=7.1.0; extra == 'dev'
